shaped/__init__.py
shaped/client.py
shaped/config_builders.py
shaped/query_builder.py
shaped/autogen/__init__.py
shaped/autogen/api_client.py
shaped/autogen/api_response.py
shaped/autogen/configuration.py
shaped/autogen/exceptions.py
shaped/autogen/rest.py
shaped/autogen/api/__init__.py
shaped/autogen/api/engine_api.py
shaped/autogen/api/query_api.py
shaped/autogen/api/table_api.py
shaped/autogen/api/view_api.py
shaped/autogen/models/__init__.py
shaped/autogen/models/ai_enrichment_view_config.py
shaped/autogen/models/algorithm.py
shaped/autogen/models/amplitude_table_config.py
shaped/autogen/models/attn_dropout_prob.py
shaped/autogen/models/attribute_journey.py
shaped/autogen/models/attribute_value.py
shaped/autogen/models/autoscaling_config.py
shaped/autogen/models/aws_pinpoint_table_config.py
shaped/autogen/models/batch_size.py
shaped/autogen/models/batch_size1.py
shaped/autogen/models/batch_size2.py
shaped/autogen/models/big_query_table_config.py
shaped/autogen/models/bm25.py
shaped/autogen/models/boosted_reorder_step.py
shaped/autogen/models/canary_rollout.py
shaped/autogen/models/candidate_attributes_retrieve_step.py
shaped/autogen/models/candidate_ids_retrieve_step.py
shaped/autogen/models/candidate_retrieval_strategy.py
shaped/autogen/models/clickhouse_table_config.py
shaped/autogen/models/column_order_retrieve_step.py
shaped/autogen/models/column_ordering.py
shaped/autogen/models/create_table_response.py
shaped/autogen/models/create_view_response.py
shaped/autogen/models/custom_table_config.py
shaped/autogen/models/data_compute_config.py
shaped/autogen/models/data_config.py
shaped/autogen/models/data_config_interaction_table.py
shaped/autogen/models/data_split_config.py
shaped/autogen/models/data_split_strategy.py
shaped/autogen/models/data_tier.py
shaped/autogen/models/default.py
shaped/autogen/models/delete_engine_response.py
shaped/autogen/models/delete_table_response.py
shaped/autogen/models/delete_view_response.py
shaped-2.0.5.dist-info/METADATA
shaped-2.0.5.dist-info/WHEEL
shaped-2.0.5.dist-info/entry_points.txt
shaped-2.0.5.dist-info/top_level.txt
shaped-2.0.5.dist-info/zip-safe
shaped-2.0.5.dist-info/RECORD
