Metadata-Version: 2.4
Name: shaped
Version: 2.0.5
Summary: CLI and SDK tools for interacting with the Shaped API.
Home-page: https://github.com/shaped-ai/magnus
Author: Shaped Team
Author-email: support@shaped.ai
Keywords: shaped-ai
Classifier: Operating System :: POSIX :: Linux
Classifier: Operating System :: MacOS :: MacOS X
Classifier: Programming Language :: Python :: 3
Classifier: Development Status :: 5 - Production/Stable
Classifier: Intended Audience :: Developers
Requires-Python: >=3.9, <3.14
Requires-Dist: pyarrow==20.0.0
Requires-Dist: pandas==2.3.0
Requires-Dist: numpy==1.26.4
Requires-Dist: typer==0.7.0
Requires-Dist: click==8.2.1
Requires-Dist: requests>=2.28.1
Requires-Dist: pydantic>=2.8.2
Requires-Dist: pyyaml>=6.0
Requires-Dist: tqdm==4.67.1
Requires-Dist: s3fs==0.4.2
Requires-Dist: fsspec==2023.5.0
Requires-Dist: urllib3>=2.2.3
Requires-Dist: h2>=4.0.0
Requires-Dist: python-dateutil
Requires-Dist: typing-extensions>=4.7.1
Requires-Dist: pytest==8.4.1
Requires-Dist: pytest-mock==3.14.0
Dynamic: author
Dynamic: author-email
Dynamic: classifier
Dynamic: description
Dynamic: description-content-type
Dynamic: home-page
Dynamic: keywords
Dynamic: requires-dist
Dynamic: requires-python
Dynamic: summary
